noworkflow/__init__.py
noworkflow/__main__.py
noworkflow/jupyter/extension.js
noworkflow/jupyter/extension.js.map
noworkflow/jupyter/index.js
noworkflow/jupyter/index.js.map
noworkflow/now/__init__.py
noworkflow/now/cmd/__init__.py
noworkflow/now/cmd/cmd_dataflow.py
noworkflow/now/cmd/cmd_debug.py
noworkflow/now/cmd/cmd_demo.py
noworkflow/now/cmd/cmd_diff.py
noworkflow/now/cmd/cmd_export.py
noworkflow/now/cmd/cmd_gc.py
noworkflow/now/cmd/cmd_helper.py
noworkflow/now/cmd/cmd_history.py
noworkflow/now/cmd/cmd_list.py
noworkflow/now/cmd/cmd_restore.py
noworkflow/now/cmd/cmd_run.py
noworkflow/now/cmd/cmd_schema.py
noworkflow/now/cmd/cmd_show.py
noworkflow/now/cmd/cmd_vis.py
noworkflow/now/cmd/command.py
noworkflow/now/collection/__init__.py
noworkflow/now/collection/metadata.py
noworkflow/now/collection/prov_definition/__init__.py
noworkflow/now/collection/prov_definition/definition.py
noworkflow/now/collection/prov_definition/function_visitor.py
noworkflow/now/collection/prov_definition/slicing_visitor.py
noworkflow/now/collection/prov_definition/utils.py
noworkflow/now/collection/prov_deployment/__init__.py
noworkflow/now/collection/prov_deployment/deployment.py
noworkflow/now/collection/prov_execution/__init__.py
noworkflow/now/collection/prov_execution/argument_captors.py
noworkflow/now/collection/prov_execution/base.py
noworkflow/now/collection/prov_execution/debugger.py
noworkflow/now/collection/prov_execution/execution.py
noworkflow/now/collection/prov_execution/profiler.py
noworkflow/now/collection/prov_execution/slicing.py
noworkflow/now/ipython/__init__.py
noworkflow/now/ipython/converter.py
noworkflow/now/ipython/hierarchymagic.py
noworkflow/now/ipython/magics/__init__.py
noworkflow/now/ipython/magics/command.py
noworkflow/now/ipython/magics/now_ipython.py
noworkflow/now/ipython/magics/now_ls_magic.py
noworkflow/now/ipython/magics/now_prolog.py
noworkflow/now/ipython/magics/now_restore.py
noworkflow/now/ipython/magics/now_run.py
noworkflow-1.12.0.dist-info/METADATA
noworkflow-1.12.0.dist-info/WHEEL
noworkflow-1.12.0.dist-info/entry_points.txt
noworkflow-1.12.0.dist-info/top_level.txt
noworkflow-1.12.0.dist-info/RECORD
